ecs/__init__.py
ecs/ai_tools.py
ecs/audit.py
ecs/core.py
ecs/crypto.py
ecs_eurocybersecurite-0.3.4.dist-info/licenses/LICENSE
ecs_eurocybersecurite-0.3.4.dist-info/METADATA
ecs_eurocybersecurite-0.3.4.dist-info/WHEEL
ecs_eurocybersecurite-0.3.4.dist-info/entry_points.txt
ecs_eurocybersecurite-0.3.4.dist-info/top_level.txt
ecs_eurocybersecurite-0.3.4.dist-info/RECORD
