Metadata-Version: 2.4
Name: ecs-eurocybersecurite
Version: 0.3.4
Summary: Cybersecurity and AI tools by Eurocybersecurite
Home-page: https://github.com/tuteur1/RooR
Author: Mohamed Redha Abdessemed
Author-email: mohamed.abdessemed@eurocybersecurite.fr
License: MIT
Project-URL: Documentation, https://eurocybersecurite.fr/auth/login.php
Project-URL: Source, https://github.com/tuteur1/RooR.git
Project-URL: Issues, https://github.com/tuteur1/RooR/issues
Keywords: cybersecurity,AI,tools,python
Classifier: Development Status :: 3 - Alpha
Classifier: Intended Audience :: Developers
Classifier: Topic :: Security
Classifier: Programming Language :: Python :: 3
Classifier: License :: OSI Approved :: MIT License
Classifier: Operating System :: OS Independent
Requires-Python: >=3.9
License-File: LICENSE
Requires-Dist: flask
Requires-Dist: transformers
Requires-Dist: torch
Requires-Dist: scikit-learn
Dynamic: author
Dynamic: author-email
Dynamic: classifier
Dynamic: description
Dynamic: description-content-type
Dynamic: home-page
Dynamic: keywords
Dynamic: license
Dynamic: license-file
Dynamic: project-url
Dynamic: requires-dist
Dynamic: requires-python
Dynamic: summary
